reacher/reacher.py
reacher-0.4.1.dist-info/METADATA
reacher-0.4.1.dist-info/WHEEL
reacher-0.4.1.dist-info/top_level.txt
reacher-0.4.1.dist-info/RECORD
